{"stat.useItem.61":2,"stat.craftItem.61":1,"stat.leaveGame":4,"stat.mineBlock.16":44,"stat.mineBlock.15":8,"stat.mineBlock.18":4,"stat.mineBlock.17":12,"stat.swimOneCm":5661,"stat.jump":1978,"stat.fallOneCm":513736,"stat.climbOneCm":1872,"achievement.buildWorkBench":1,"achievement.exploreAllBiomes":{"value":0,"progress":["Cold Taiga","Sunflower Plains","Cold Taiga Hills","Birch Forest","Extreme Hills M","Time Chamber","Beach","FrozenRiver","Extreme Hills+","Cold Beach","River","Ocean","Taiga","Swampland","Ice Mountains","ForestHills","Flower Forest","Cold Taiga M","Plains","TaigaHills","Other World type 4","Other World type 2","Ice Plains","Jungle","Forest","Extreme Hills","Dirty Stony","Deep Ocean"]},"stat.craftItem.364":37,"stat.craftItem.366":8,"stat.craftItem.5":44,"stat.damageTaken":1673885,"stat.mineBlock.1":53,"stat.mineBlock.61":1,"stat.flyOneCm":1915196,"stat.useItem.50":35,"achievement.buildPickaxe":2,"stat.damageDealt":27450,"achievement.buildBetterPickaxe":1,"stat.killEntity.Cow":13,"stat.useItem.58":2,"stat.useItem.274":95,"stat.useItem.275":2,"stat.walkOneCm":1007158,"stat.mineBlock.175":3,"stat.killEntity.Creeper":4,"stat.mineBlock.58":2,"achievement.mineWood":11,"stat.useItem.35":3,"stat.killEntity.Skeleton":7,"stat.craftItem.320":99,"achievement.openInventory":102,"stat.killEntity.Chicken":10,"stat.craftItem.280":16,"stat.killEntity.Spider":1,"stat.mobKills":176,"achievement.buildFurnace":1,"stat.craftItem.274":1,"stat.craftItem.58":1,"stat.craftItem.275":1,"stat.mineBlock.37":3,"stat.deaths":3,"stat.drop":120,"stat.playOneMinute":232573,"stat.craftItem.50":40,"stat.killEntity.Sheep":8,"stat.craftItem.270":1,"stat.useItem.3":10,"stat.killEntity.Zombie":21,"stat.useItem.270":11,"stat.mineBlock.31":89,"stat.diveOneCm":31972}